pyBAKS/BAKS.py
pyBAKS/BAKS_test.py
pyBAKS/__init__.py
pyBAKS-0.1.8.dist-info/CHANGES.txt
pyBAKS-0.1.8.dist-info/METADATA
pyBAKS-0.1.8.dist-info/WHEEL
pyBAKS-0.1.8.dist-info/top_level.txt
pyBAKS-0.1.8.dist-info/RECORD
